charbox/__init__.py
charbox/config.py
charbox/initializer.py
charbox-0.0.5.dist-info/licenses/LICENSE
charbox-0.0.5.dist-info/METADATA
charbox-0.0.5.dist-info/WHEEL
charbox-0.0.5.dist-info/top_level.txt
charbox-0.0.5.dist-info/RECORD
