Metadata-Version: 2.4
Name: charbox
Version: 0.0.5
Summary: CharBox is a Python library that generates random character attributes, including names, hair colors, and eye colors. It supports multiple name origins and offers standard and fancy variations for hair and eye colors.
Home-page: https://github.com/TaireruLLC/charbox
Author: Taireru LLC
Author-email: tairerullc@gmail.com
License: MIT
Classifier: Programming Language :: Python :: 3
Classifier: Operating System :: OS Independent
Requires-Python: >=3.6
License-File: LICENSE
Requires-Dist: altcolor>=0.0.5
Dynamic: author
Dynamic: author-email
Dynamic: classifier
Dynamic: description
Dynamic: description-content-type
Dynamic: home-page
Dynamic: license
Dynamic: license-file
Dynamic: requires-dist
Dynamic: requires-python
Dynamic: summary
